odoo/addons/delivery_carrier_image/README.rst
odoo/addons/delivery_carrier_image/__init__.py
odoo/addons/delivery_carrier_image/__manifest__.py
odoo/addons/delivery_carrier_image/i18n/delivery_carrier_image.pot
odoo/addons/delivery_carrier_image/i18n/it.po
odoo/addons/delivery_carrier_image/models/__init__.py
odoo/addons/delivery_carrier_image/models/delivery_carrier.py
odoo/addons/delivery_carrier_image/readme/CONFIGURE.md
odoo/addons/delivery_carrier_image/readme/CONTRIBUTORS.md
odoo/addons/delivery_carrier_image/readme/DESCRIPTION.md
odoo/addons/delivery_carrier_image/static/description/icon.png
odoo/addons/delivery_carrier_image/static/description/index.html
odoo/addons/delivery_carrier_image/tests/__init__.py
odoo/addons/delivery_carrier_image/tests/test_image.py
odoo/addons/delivery_carrier_image/views/delivery_carrier.xml
odoo_addon_delivery_carrier_image-18.0.1.0.0.4.dist-info/METADATA
odoo_addon_delivery_carrier_image-18.0.1.0.0.4.dist-info/WHEEL
odoo_addon_delivery_carrier_image-18.0.1.0.0.4.dist-info/top_level.txt
odoo_addon_delivery_carrier_image-18.0.1.0.0.4.dist-info/RECORD
